[{"id":1,"addon_key":"OrderManagement","addon_profile_id":0,"addon_title":"Order Management","description":"Offline PaymentOrder Management","tags":"Order Management","image_300x300":"addon-card-1.jpg","purchase_price":0,"addon_version":"''","purchase_link":"''","addon_preview":"''","is_install":1,"discount":0,"is_active":"1","deleted_at":null,"created_at":"2021-08-22 21:56:03","updated_at":null},{"id":2,"addon_key":"ProductManagement","addon_profile_id":0,"addon_title":"Product Management","description":"Seller Subscription Addon will add a new feature to create a\n                                                    subscription package for you sellers\/vendors. You can create\n                                                    unlimited packages.","tags":"Product Management","image_300x300":"addon-card-2.jpg","purchase_price":0,"addon_version":"1.0","purchase_link":"''","addon_preview":"''","is_install":0,"discount":0,"is_active":"1","deleted_at":null,"created_at":"2021-08-21 00:04:53","updated_at":null},{"id":3,"addon_key":"''","addon_profile_id":0,"addon_title":"Point of Sale","description":"Point of Sale","tags":"Point of Sale","image_300x300":"addon-card-3.jpg","purchase_price":0,"addon_version":"''","purchase_link":"''","addon_preview":"''","is_install":1,"discount":0,"is_active":1,"deleted_at":null,"created_at":"2021-08-21 00:05:21","updated_at":null},{"id":4,"addon_key":"''","addon_profile_id":0,"addon_title":"Paytm","description":"Paytm","tags":"Paytm","image_300x300":"addon-card-4.jpg","purchase_price":0,"addon_version":"''","purchase_link":"''","addon_preview":"''","is_install":1,"discount":0,"is_active":1,"deleted_at":null,"created_at":"2021-08-21 00:05:41","updated_at":null},{"id":5,"addon_key":"''","addon_profile_id":0,"addon_title":"Seller Subscription System","description":"Seller Subscription System","tags":"Seller Subscription System","image_300x300":"addon-card-5.jpg","purchase_price":0,"addon_version":"''","purchase_link":"''","addon_preview":"''","is_install":1,"discount":0,"is_active":1,"deleted_at":null,"created_at":"2021-08-21 00:04:53","updated_at":null},{"id":6,"addon_key":"''","addon_profile_id":0,"addon_title":"OTP","description":"OTP","tags":"OTP","image_300x300":"addon-card-6.jpg","purchase_price":0,"addon_version":"''","purchase_link":"''","addon_preview":"''","is_install":1,"discount":0,"is_active":"1","deleted_at":null,"created_at":"2021-08-21 00:05:21","updated_at":null},{"id":7,"addon_key":"''","addon_profile_id":0,"addon_title":"Refund","description":"Refund","tags":"Refund","image_300x300":"addon-card-1.jpg","purchase_price":0,"addon_version":"''","purchase_link":"''","addon_preview":"''","is_install":1,"discount":0,"is_active":1,"deleted_at":null,"created_at":"2021-08-21 00:05:41","updated_at":null}]